Microlensify/__init__.py
Microlensify/__main__.py
Microlensify/core.py
Microlensify/model.py
microlensify-1.0.8.dist-info/licenses/LICENSE
microlensify-1.0.8.dist-info/METADATA
microlensify-1.0.8.dist-info/WHEEL
microlensify-1.0.8.dist-info/entry_points.txt
microlensify-1.0.8.dist-info/top_level.txt
microlensify-1.0.8.dist-info/RECORD
