Metadata-Version: 2.4
Name: Microlensify
Version: 1.0.8
Summary: Microlensing Single Lens Classification – Atousa Kalantari & Somayeh Khakpash
Author-email: Atousa Kalantari <atousakalantari99@gmail.com>
License: MIT
Project-URL: Homepage, https://github.com/Atousa-Kalantari/Microlensify
Project-URL: Repository, https://github.com/Atousa-Kalantari/Microlensify
Requires-Python: >=3.9
License-File: LICENSE
Provides-Extra: core
Requires-Dist: numpy>=1.21; extra == "core"
Requires-Dist: pandas; extra == "core"
Requires-Dist: astropy; extra == "core"
Requires-Dist: joblib; extra == "core"
Requires-Dist: tqdm; extra == "core"
Provides-Extra: ml
Requires-Dist: tensorflow>=2.15; extra == "ml"
Requires-Dist: scikit-learn; extra == "ml"
Provides-Extra: full
Requires-Dist: Microlensify[core]; extra == "full"
Requires-Dist: Microlensify[ml]; extra == "full"
Dynamic: license-file
